[
  {
    "funName": "Travnik Old Town",
    "imageFile": "https://example.com/travnik_old_town.jpg",
    "description": "Explore the charm of Travnik's Old Town, with its historic architecture, cobblestone streets, and cultural significance. A journey through time in the heart of the city.",
    "duration": "2h",
    "price": "Free",
    "address": "6MHC+V74, Travnik",
    "type": "historical",
    "location": "44.22964545388832, 17.670713911663512"
  },
  {
    "funName": "Plava Voda",
    "imageFile": "https://example.com/plava_voda.jpg",
    "description": "Experience the beauty of Plava Voda, a serene natural attraction surrounded by lush greenery. Perfect for a peaceful retreat and connecting with nature.",
    "duration": "Flexible",
    "price": "Free",
    "address": "44.23027035824724, 17.671774323085085",
    "type": "nature",
    "location": "44.23027035824724, 17.671774323085085"
  },
  {
    "funName": "Ilhamijino Turbe",
    "imageFile": "https://example.com/ilhamijino_turbe.jpg",
    "description": "Discover Ilhamijino Turbe, a historical site with architectural beauty and cultural significance. Immerse yourself in the rich heritage of Potur Mahala, Travnik.",
    "duration": "1.5h",
    "price": "Free",
    "address": "6MH7+36R, Potur Mahala, Travnik",
    "type": "historical",
    "location": "44.22766775478569, 17.66305861687128"
  },
  {
    "funName": "Zavicajni Muzej Travnik",
    "imageFile": "https://example.com/zavicajni_muzej_travnik.jpg",
    "description": "Explore the local history and heritage at Zavicajni Muzej Travnik. A museum showcasing the cultural richness of Travnik with exhibits and artifacts.",
    "duration": "2h",
    "price": "Free",
    "address": "Mehmed-paše Kukavice 1, Travnik 72270",
    "type": "museum",
    "location": "44.22567603283224, 17.666582686601206"
  },
  {
    "funName": "Sahat Kula",
    "imageFile": "https://example.com/sahat_kula.jpg",
    "description": "Visit Sahat Kula, a historic clock tower located at Vezirska Street, Travnik. Admire the architectural beauty and enjoy panoramic views of the city.",
    "duration": "1h",
    "price": "Free",
    "address": "Vezirska 2, Travnik 72270",
    "type": "historical",
    "location": "44.22611521253636, 17.659724507445098"
  },
  {
    "funName": "Spomenik Bosanskih Vezira",
    "imageFile": "https://example.com/spomenik_bosanskih_vezira.jpg",
    "description": "Pay homage to the Bosnian Viziers at this monument located at Bosanska Street, Travnik. A symbol of historical significance and cultural pride.",
    "duration": "1.5h",
    "price": "Free",
    "address": "Bosanska 56, Travnik 72270",
    "type": "monument",
    "location": "44.22659118772349, 17.660894277017487"
  },
  {
    "funName": "Vrata Medrese Mehmed Paše Kukavice",
    "imageFile": "https://example.com/vrata_medrese_mehmed_pase_kukavice.jpg",
    "description": "Step into history at the gates of Medresa Mehmed Paše Kukavice, located at Bosanska bb, Travnik 72270. Experience the architectural grandeur of the past.",
    "duration": "1h",
    "price": "Free",
    "address": "Bosanska bb, Travnik 72270",
    "type": "historical",
    "location": "44.22638275383969, 17.661452824268967"
  },
  {
    "funName": "Ćiro u Travniku",
    "imageFile": "https://example.com/ciro_u_travniku.jpg",
    "description": "Embark on a nostalgic journey with Ćiro u Travniku. Explore the heritage of the famous narrow-gauge railway that once connected Travnik to the world.",
    "duration": "2h",
    "price": "Free",
    "address": "Bosanska 145, Travnik 72270",
    "type": "historical",
    "location": "44.22591786743656, 17.66637123566945"
  },
  {
    "funName": "Ljuljačka, Galica, Vlašić",
    "imageFile": "https://example.com/ljuljacka_galica_vlasic.jpg",
    "description": "Experience the thrill of the giant swing at Galica, Vlašić. A unique attraction offering panoramic views and adrenaline-pumping excitement.",
    "duration": "1h",
    "price": "10 KM",
    "address": "7JG4+F55, Galica, Šišava",
    "type": "adventure",
    "location": ""
  },
  {
    "funName": "Vidikovac Vukovića Brdo",
    "imageFile": "https://example.com/vidikovac_vukovica_brdo.jpg",
    "description": "Reach new heights at Vidikovac Vukovića Brdo. Enjoy breathtaking views of the surrounding landscapes from this elevated vantage point in Travnik.",
    "duration": "1.5h",
    "price": "Free",
    "address": "7HG8+H7W, Travnik",
    "type": "scenic",
    "location": "44.23155489078539, 17.636760575997354"
  },
  {
    "funName": "RELEJ VLAŠIĆ",
    "imageFile": "https://example.com/relej_vlasic.jpg",
    "description": "Visit the RELEJ VLAŠIĆ, a key attraction in Šišava. Experience the beauty of Vlašić and enjoy various recreational activities at this mountain relay station.",
    "duration": "Flexible",
    "price": "Varies",
    "address": "7JVP+4F, Šišava",
    "type": "recreational",
    "location": "44.29262450348578, 17.63633343269761"
  },
  {
    "funName": "Sahat Kula na Musali",
    "imageFile": "https://example.com/sahat_kula_musala.jpg",
    "description": "Explore the Sahat Kula on Musala, a historical clock tower with a unique charm. Dive into the cultural heritage of Musala in Travnik.",
    "duration": "1h",
    "price": "Free",
    "address": "M-5, Travnik",
    "type": "historical",
    "location": "44.22721203671289, 17.670487942422998"
  }
]
